PQAnalysis/__init__.py
PQAnalysis/_version.py
PQAnalysis/config.py
PQAnalysis/exceptions.py
PQAnalysis/formats.py
PQAnalysis/type_checking.py
PQAnalysis/types.py
PQAnalysis/analysis/__init__.py
PQAnalysis/analysis/rdf/__init__.py
PQAnalysis/analysis/rdf/api.py
PQAnalysis/analysis/rdf/exceptions.py
PQAnalysis/analysis/rdf/rdf.py
PQAnalysis/analysis/rdf/rdf_input_file_reader.py
PQAnalysis/analysis/rdf/rdf_output_file_writer.py
PQAnalysis/atomic_system/__init__.py
PQAnalysis/atomic_system/_decorators.py
PQAnalysis/atomic_system/_positions.py
PQAnalysis/atomic_system/_properties.py
PQAnalysis/atomic_system/_standard_properties.py
PQAnalysis/atomic_system/atomic_system.py
PQAnalysis/atomic_system/exceptions.py
PQAnalysis/cli/__init__.py
PQAnalysis/cli/_argument_parser.py
PQAnalysis/cli/_cli_base.py
PQAnalysis/cli/add_molecules.py
PQAnalysis/cli/build_nep_traj.py
PQAnalysis/cli/continue_input.py
PQAnalysis/cli/gen2xyz.py
PQAnalysis/cli/main.py
PQAnalysis/cli/rdf.py
PQAnalysis/cli/rst2xyz.py
PQAnalysis/cli/traj2box.py
PQAnalysis/cli/traj2qmcfc.py
PQAnalysis/cli/xyz2gen.py
PQAnalysis/core/__init__.py
PQAnalysis/core/api.py
PQAnalysis/core/exceptions.py
PQAnalysis/core/residue.py
PQAnalysis/core/atom/__init__.py
PQAnalysis/core/atom/atom.py
PQAnalysis/core/atom/element.py
PQAnalysis/core/cell/__init__.py
PQAnalysis/core/cell/_standard_properties.py
PQAnalysis/core/cell/cell.py
PQAnalysis/grammar/PQ_inputGrammar.lark
PQAnalysis/grammar/inputGrammar.lark
PQAnalysis/grammar/rules.lark
PQAnalysis/grammar/selection.lark
PQAnalysis/grammar/terminals.lark
PQAnalysis/io/__init__.py
PQAnalysis/io/api.py
PQAnalysis/io/base.py
PQAnalysis/io/box_writer.py
PQAnalysis/io/conversion_api.py
PQAnalysis/io/energy_file_reader.py
PQAnalysis/io/exceptions.py
PQAnalysis/io/formats.py
PQAnalysis/io/info_file_reader.py
PQAnalysis/io/moldescriptor_reader.py
PQAnalysis/io/write_api.py
PQAnalysis/io/gen_file/__init__.py
PQAnalysis/io/gen_file/api.py
PQAnalysis/io/gen_file/exceptions.py
PQAnalysis-1.1.2.dist-info/LICENSE
PQAnalysis-1.1.2.dist-info/METADATA
PQAnalysis-1.1.2.dist-info/WHEEL
PQAnalysis-1.1.2.dist-info/entry_points.txt
PQAnalysis-1.1.2.dist-info/top_level.txt
PQAnalysis-1.1.2.dist-info/RECORD
