Metadata-Version: 2.1
Name: PQAnalysis
Version: 1.1.2
Summary: PQAnalysis is a python package for the analysis of PQ simulations.
Author-email: Jakob Gamper <97gamjak@gmail.com>, "Josef M. Gallmetzer" <gallmetzer.josef@gmail.com>, "Clarissa A. Seidler" <clarissa.seidler@gmail.com>
Project-URL: Homepage, https://github.com/MolarVerse/PQAnalysis
Project-URL: PQ, https://github.com/MolarVerse/PQ
Classifier: Programming Language :: Python :: 3
Classifier: License :: OSI Approved :: MIT License
Classifier: Operating System :: OS Independent
Requires-Python: >=3.12
License-File: LICENSE
Requires-Dist: numpy
Requires-Dist: scipy
Requires-Dist: beartype
Requires-Dist: multimethod
Requires-Dist: lark
Requires-Dist: tqdm
Requires-Dist: decorator
Requires-Dist: argcomplete
Requires-Dist: yapf
Requires-Dist: rich-argparse
Provides-Extra: docs
Requires-Dist: sphinx ; extra == 'docs'
Requires-Dist: sphinx-sitemap ; extra == 'docs'
Requires-Dist: myst-parser ; extra == 'docs'
Requires-Dist: sphinx-rtd-theme ; extra == 'docs'
Requires-Dist: better-apidoc ; extra == 'docs'
Requires-Dist: six ; extra == 'docs'
Requires-Dist: docstr-coverage ; extra == 'docs'
Provides-Extra: test
Requires-Dist: pytest ; extra == 'test'
Requires-Dist: coverage ; extra == 'test'
Requires-Dist: pytest-cov ; extra == 'test'
Requires-Dist: pylint ; extra == 'test'
Requires-Dist: pylint-django ; extra == 'test'
Requires-Dist: docstr-coverage ; extra == 'test'
